[
  {
    "id": 1,
    "name": "清华大学",
    "code": "10001",
    "location": "北京",
    "type": "综合",
    "is_985": true,
    "is_211": true,
    "is_double_first_class": true,
    "project_type": "A 类"
  },
  {
    "id": 2,
    "name": "北京大学",
    "code": "10002",
    "location": "北京",
    "type": "综合",
    "is_985": true,
    "is_211": true,
    "is_double_first_class": true,
    "project_type": "A 类"
  },
  {
    "id": 3,
    "name": "中国人民大学",
    "code": "10003",
    "location": "未知",
    "type": "综合",
    "is_985": true,
    "is_211": true,
    "is_double_first_class": true,
    "project_type": "A 类"
  },
  {
    "id": 4,
    "name": "北京师范大学",
    "code": "10004",
    "location": "北京",
    "type": "师范",
    "is_985": true,
    "is_211": true,
    "is_double_first_class": true,
    "project_type": "A 类"
  },
  {
    "id": 5,
    "name": "北京理工大学",
    "code": "10005",
    "location": "北京",
    "type": "理工",
    "is_985": true,
    "is_211": true,
    "is_double_first_class": true,
    "project_type": "A 类"
  },
  {
    "id": 6,
    "name": "北京航空航天大学",
    "code": "10006",
    "location": "北京",
    "type": "综合",
    "is_985": true,
    "is_211": true,
    "is_double_first_class": true,
    "project_type": "A 类"
  },
  {
    "id": 7,
    "name": "中国农业大学",
    "code": "10007",
    "location": "未知",
    "type": "农林",
    "is_985": true,
    "is_211": true,
    "is_double_first_class": true,
    "project_type": "A 类"
  },
  {
    "id": 8,
    "name": "中央民族大学",
    "code": "10008",
    "location": "未知",
    "type": "民族",
    "is_985": true,
    "is_211": true,
    "is_double_first_class": true,
    "project_type": "A 类"
  },
  {
    "id": 9,
    "name": "南开大学",
    "code": "10009",
    "location": "天津",
    "type": "综合",
    "is_985": true,
    "is_211": true,
    "is_double_first_class": true,
    "project_type": "A 类"
  },
  {
    "id": 10,
    "name": "天津大学",
    "code": "10010",
    "location": "天津",
    "type": "综合",
    "is_985": true,
    "is_211": true,
    "is_double_first_class": true,
    "project_type": "A 类"
  },
  {
    "id": 11,
    "name": "大连理工大学",
    "code": "10011",
    "location": "辽宁大连",
    "type": "理工",
    "is_985": true,
    "is_211": true,
    "is_double_first_class": true,
    "project_type": "A 类"
  },
  {
    "id": 12,
    "name": "东北大学",
    "code": "10012",
    "location": "北京",
    "type": "综合",
    "is_985": true,
    "is_211": true,
    "is_double_first_class": true,
    "project_type": "A 类"
  },
  {
    "id": 13,
    "name": "吉林大学",
    "code": "10013",
    "location": "吉林长春",
    "type": "综合",
    "is_985": true,
    "is_211": true,
    "is_double_first_class": true,
    "project_type": "A 类"
  },
  {
    "id": 14,
    "name": "哈尔滨工业大学",
    "code": "10014",
    "location": "黑龙江哈尔滨",
    "type": "理工",
    "is_985": true,
    "is_211": true,
    "is_double_first_class": true,
    "project_type": "A 类"
  },
  {
    "id": 15,
    "name": "复旦大学",
    "code": "10015",
    "location": "上海",
    "type": "综合",
    "is_985": true,
    "is_211": true,
    "is_double_first_class": true,
    "project_type": "A 类"
  },
  {
    "id": 16,
    "name": "同济大学",
    "code": "10016",
    "location": "上海",
    "type": "综合",
    "is_985": true,
    "is_211": true,
    "is_double_first_class": true,
    "project_type": "A 类"
  },
  {
    "id": 17,
    "name": "上海交通大学",
    "code": "10017",
    "location": "上海",
    "type": "综合",
    "is_985": true,
    "is_211": true,
    "is_double_first_class": true,
    "project_type": "A 类"
  },
  {
    "id": 18,
    "name": "华东师范大学",
    "code": "10018",
    "location": "未知",
    "type": "师范",
    "is_985": true,
    "is_211": true,
    "is_double_first_class": true,
    "project_type": "A 类"
  },
  {
    "id": 19,
    "name": "南京大学",
    "code": "10019",
    "location": "江苏南京",
    "type": "综合",
    "is_985": true,
    "is_211": true,
    "is_double_first_class": true,
    "project_type": "A 类"
  },
  {
    "id": 20,
    "name": "东南大学",
    "code": "10020",
    "location": "江苏南京",
    "type": "综合",
    "is_985": true,
    "is_211": true,
    "is_double_first_class": true,
    "project_type": "A 类"
  },
  {
    "id": 21,
    "name": "浙江大学",
    "code": "10021",
    "location": "浙江杭州",
    "type": "综合",
    "is_985": true,
    "is_211": true,
    "is_double_first_class": true,
    "project_type": "A 类"
  },
  {
    "id": 22,
    "name": "中国科学技术大学",
    "code": "10022",
    "location": "安徽合肥",
    "type": "综合",
    "is_985": true,
    "is_211": true,
    "is_double_first_class": true,
    "project_type": "A 类"
  },
  {
    "id": 23,
    "name": "厦门大学",
    "code": "10023",
    "location": "福建厦门",
    "type": "综合",
    "is_985": true,
    "is_211": true,
    "is_double_first_class": true,
    "project_type": "A 类"
  },
  {
    "id": 24,
    "name": "山东大学",
    "code": "10024",
    "location": "山东济南",
    "type": "综合",
    "is_985": true,
    "is_211": true,
    "is_double_first_class": true,
    "project_type": "A 类"
  },
  {
    "id": 25,
    "name": "中国海洋大学",
    "code": "10025",
    "location": "山东青岛",
    "type": "综合",
    "is_985": true,
    "is_211": true,
    "is_double_first_class": true,
    "project_type": "A 类"
  },
  {
    "id": 26,
    "name": "武汉大学",
    "code": "10026",
    "location": "湖北武汉",
    "type": "综合",
    "is_985": true,
    "is_211": true,
    "is_double_first_class": true,
    "project_type": "A 类"
  },
  {
    "id": 27,
    "name": "华中科技大学",
    "code": "10027",
    "location": "湖北武汉",
    "type": "理工",
    "is_985": true,
    "is_211": true,
    "is_double_first_class": true,
    "project_type": "A 类"
  },
  {
    "id": 28,
    "name": "中南大学",
    "code": "10028",
    "location": "湖南长沙",
    "type": "综合",
    "is_985": true,
    "is_211": true,
    "is_double_first_class": true,
    "project_type": "A 类"
  },
  {
    "id": 29,
    "name": "湖南大学",
    "code": "10029",
    "location": "湖南长沙",
    "type": "综合",
    "is_985": true,
    "is_211": true,
    "is_double_first_class": true,
    "project_type": "A 类"
  },
  {
    "id": 30,
    "name": "中山大学",
    "code": "10030",
    "location": "广东广州",
    "type": "综合",
    "is_985": true,
    "is_211": true,
    "is_double_first_class": true,
    "project_type": "A 类"
  },
  {
    "id": 31,
    "name": "华南理工大学",
    "code": "10031",
    "location": "广东广州",
    "type": "理工",
    "is_985": true,
    "is_211": true,
    "is_double_first_class": true,
    "project_type": "A 类"
  },
  {
    "id": 32,
    "name": "四川大学",
    "code": "10032",
    "location": "未知",
    "type": "综合",
    "is_985": true,
    "is_211": true,
    "is_double_first_class": true,
    "project_type": "A 类"
  },
  {
    "id": 33,
    "name": "电子科技大学",
    "code": "10033",
    "location": "四川成都",
    "type": "理工",
    "is_985": true,
    "is_211": true,
    "is_double_first_class": true,
    "project_type": "A 类"
  },
  {
    "id": 34,
    "name": "重庆大学",
    "code": "10034",
    "location": "重庆",
    "type": "综合",
    "is_985": true,
    "is_211": true,
    "is_double_first_class": true,
    "project_type": "A 类"
  },
  {
    "id": 35,
    "name": "西安交通大学",
    "code": "10035",
    "location": "陕西西安",
    "type": "综合",
    "is_985": true,
    "is_211": true,
    "is_double_first_class": true,
    "project_type": "A 类"
  },
  {
    "id": 36,
    "name": "西北工业大学",
    "code": "10036",
    "location": "陕西西安",
    "type": "理工",
    "is_985": true,
    "is_211": true,
    "is_double_first_class": true,
    "project_type": "A 类"
  },
  {
    "id": 37,
    "name": "兰州大学",
    "code": "10037",
    "location": "甘肃兰州",
    "type": "综合",
    "is_985": true,
    "is_211": true,
    "is_double_first_class": true,
    "project_type": "B 类"
  },
  {
    "id": 38,
    "name": "国防科技大学",
    "code": "10038",
    "location": "未知",
    "type": "理工",
    "is_985": true,
    "is_211": true,
    "is_double_first_class": true,
    "project_type": "B 类"
  },
  {
    "id": 39,
    "name": "西北农林科技大学",
    "code": "10039",
    "location": "陕西西安",
    "type": "理工",
    "is_985": true,
    "is_211": true,
    "is_double_first_class": true,
    "project_type": "B 类"
  },
  {
    "id": 40,
    "name": "北京交通大学",
    "code": "10040",
    "location": "北京",
    "type": "综合",
    "is_985": false,
    "is_211": true,
    "is_double_first_class": true,
    "project_type": null
  },
  {
    "id": 41,
    "name": "北京科技大学",
    "code": "10041",
    "location": "北京",
    "type": "理工",
    "is_985": false,
    "is_211": true,
    "is_double_first_class": true,
    "project_type": null
  },
  {
    "id": 42,
    "name": "北京化工大学",
    "code": "10042",
    "location": "北京",
    "type": "综合",
    "is_985": false,
    "is_211": true,
    "is_double_first_class": true,
    "project_type": null
  },
  {
    "id": 43,
    "name": "北京邮电大学",
    "code": "10043",
    "location": "北京",
    "type": "综合",
    "is_985": false,
    "is_211": true,
    "is_double_first_class": true,
    "project_type": null
  },
  {
    "id": 44,
    "name": "北京林业大学",
    "code": "10044",
    "location": "北京",
    "type": "农林",
    "is_985": false,
    "is_211": true,
    "is_double_first_class": true,
    "project_type": null
  },
  {
    "id": 45,
    "name": "北京协和医学院",
    "code": "10045",
    "location": "北京",
    "type": "医药",
    "is_985": false,
    "is_211": true,
    "is_double_first_class": true,
    "project_type": null
  },
  {
    "id": 46,
    "name": "北京中医药大学",
    "code": "10046",
    "location": "北京",
    "type": "医药",
    "is_985": false,
    "is_211": true,
    "is_double_first_class": true,
    "project_type": null
  },
  {
    "id": 47,
    "name": "北京外国语大学",
    "code": "10047",
    "location": "北京",
    "type": "综合",
    "is_985": false,
    "is_211": true,
    "is_double_first_class": true,
    "project_type": null
  },
  {
    "id": 48,
    "name": "对外经济贸易大学",
    "code": "10048",
    "location": "未知",
    "type": "财经",
    "is_985": false,
    "is_211": true,
    "is_double_first_class": true,
    "project_type": null
  },
  {
    "id": 49,
    "name": "中央财经大学",
    "code": "10049",
    "location": "未知",
    "type": "财经",
    "is_985": false,
    "is_211": true,
    "is_double_first_class": true,
    "project_type": null
  },
  {
    "id": 50,
    "name": "中国政法大学",
    "code": "10050",
    "location": "未知",
    "type": "政法",
    "is_985": false,
    "is_211": true,
    "is_double_first_class": true,
    "project_type": null
  },
  {
    "id": 51,
    "name": "华北电力大学",
    "code": "10051",
    "location": "未知",
    "type": "综合",
    "is_985": false,
    "is_211": true,
    "is_double_first_class": true,
    "project_type": null
  },
  {
    "id": 52,
    "name": "上海财经大学",
    "code": "10052",
    "location": "上海",
    "type": "财经",
    "is_985": false,
    "is_211": true,
    "is_double_first_class": true,
    "project_type": null
  },
  {
    "id": 53,
    "name": "上海大学",
    "code": "10053",
    "location": "上海",
    "type": "综合",
    "is_985": false,
    "is_211": true,
    "is_double_first_class": true,
    "project_type": null
  },
  {
    "id": 54,
    "name": "第二军医大学",
    "code": "10054",
    "location": "未知",
    "type": "综合",
    "is_985": false,
    "is_211": true,
    "is_double_first_class": true,
    "project_type": null
  },
  {
    "id": 55,
    "name": "南京航空航天大学",
    "code": "10055",
    "location": "江苏南京",
    "type": "综合",
    "is_985": false,
    "is_211": true,
    "is_double_first_class": true,
    "project_type": null
  },
  {
    "id": 56,
    "name": "南京理工大学",
    "code": "10056",
    "location": "江苏南京",
    "type": "理工",
    "is_985": false,
    "is_211": true,
    "is_double_first_class": true,
    "project_type": null
  },
  {
    "id": 57,
    "name": "河海大学",
    "code": "10057",
    "location": "未知",
    "type": "综合",
    "is_985": false,
    "is_211": true,
    "is_double_first_class": true,
    "project_type": null
  },
  {
    "id": 58,
    "name": "南京农业大学",
    "code": "10058",
    "location": "江苏南京",
    "type": "农林",
    "is_985": false,
    "is_211": true,
    "is_double_first_class": true,
    "project_type": null
  },
  {
    "id": 59,
    "name": "中国药科大学",
    "code": "10059",
    "location": "未知",
    "type": "综合",
    "is_985": false,
    "is_211": true,
    "is_double_first_class": true,
    "project_type": null
  },
  {
    "id": 60,
    "name": "西南交通大学",
    "code": "10060",
    "location": "未知",
    "type": "综合",
    "is_985": false,
    "is_211": true,
    "is_double_first_class": true,
    "project_type": null
  },
  {
    "id": 61,
    "name": "西南财经大学",
    "code": "10061",
    "location": "未知",
    "type": "财经",
    "is_985": false,
    "is_211": true,
    "is_double_first_class": true,
    "project_type": null
  },
  {
    "id": 62,
    "name": "武汉理工大学",
    "code": "10062",
    "location": "湖北武汉",
    "type": "理工",
    "is_985": false,
    "is_211": true,
    "is_double_first_class": true,
    "project_type": null
  },
  {
    "id": 63,
    "name": "西安电子科技大学",
    "code": "10063",
    "location": "四川成都",
    "type": "理工",
    "is_985": false,
    "is_211": true,
    "is_double_first_class": true,
    "project_type": null
  },
  {
    "id": 64,
    "name": "长安大学",
    "code": "10064",
    "location": "未知",
    "type": "综合",
    "is_985": false,
    "is_211": true,
    "is_double_first_class": true,
    "project_type": null
  },
  {
    "id": 65,
    "name": "西北大学",
    "code": "10065",
    "location": "北京",
    "type": "综合",
    "is_985": false,
    "is_211": true,
    "is_double_first_class": true,
    "project_type": null
  },
  {
    "id": 66,
    "name": "辽宁大学",
    "code": "10066",
    "location": "未知",
    "type": "综合",
    "is_985": false,
    "is_211": true,
    "is_double_first_class": true,
    "project_type": null
  },
  {
    "id": 67,
    "name": "大连海事大学",
    "code": "10067",
    "location": "辽宁大连",
    "type": "综合",
    "is_985": false,
    "is_211": true,
    "is_double_first_class": true,
    "project_type": null
  }
]